iutils/__init__.py
iutils/dict.py
iutils/utils.py
iutils/tests/__init__.py
iutils/tests/test_dict.py
iutils/tests/test_utils.py
pcolrm/__init__.py
pcolrm/commands.py
pcolrm/pcolrm.py
pcolrm/click/__init__.py
pcolrm/click/main.py
qaws/__init__.py
qaws/ec2.py
qaws/elb.py
qaws/qaws.py
qaws/resource.py
qaws/resources.py
qaws/route53.py
webhook/__init__.py
webhook/sites.py
webhook/webhook.py
webhook/click/__init__.py
webhook/click/main.py
iutils-0.1.0.dist-info/LICENSE.txt
iutils-0.1.0.dist-info/METADATA
iutils-0.1.0.dist-info/WHEEL
iutils-0.1.0.dist-info/entry_points.txt
iutils-0.1.0.dist-info/top_level.txt
iutils-0.1.0.dist-info/RECORD
