Metadata-Version: 2.1
Name: iutils
Version: 0.1.0
Summary: A collection of my utility modules
Home-page: https://github.com/bqbn/iutils
Author: bqbn
Author-email: bqbn@openken.com
Project-URL: Bug Reports, https://github.com/bqbn/iutils/issues
Project-URL: Source, https://github.com/bqbn/iutils
Keywords: devops utility utils
Classifier: Development Status :: 4 - Beta
Classifier: Intended Audience :: Developers
Classifier: Intended Audience :: System Administrators
Classifier: Topic :: Software Development :: Build Tools
Classifier: Programming Language :: Python :: 3
Requires-Python: <4,>=3
License-File: LICENSE.txt
Requires-Dist: awscli ~=2.17
Requires-Dist: boto3 ~=1.21
Requires-Dist: click ~=8.1
Requires-Dist: jmespath ~=1.0
Requires-Dist: requests ~=2.27
Provides-Extra: dev
Requires-Dist: build ~=1.2 ; extra == 'dev'
Requires-Dist: pipenv-setup ~=3.2 ; extra == 'dev'
Requires-Dist: twine ~=5.1 ; extra == 'dev'
Requires-Dist: wheel ~=0.34 ; extra == 'dev'
Provides-Extra: test
